dataraven/__init__.py
dataraven/common.py
dataraven/connections.py
dataraven/data_quality_operators.py
dataraven/exception_handling.py
dataraven/log.py
dataraven/measures.py
dataraven/operations.py
dataraven/test_logic.py
dataraven/tests.py
dataraven/csv/__init__.py
dataraven/csv/operations.py
dataraven/csv/reducers.py
dataraven/sql/__init__.py
dataraven/sql/core.py
dataraven/sql/helpers.py
dataraven/sql/measure_logic.py
dataraven/sql/operations.py
data_raven-1.0.0.dist-info/METADATA
data_raven-1.0.0.dist-info/WHEEL
data_raven-1.0.0.dist-info/top_level.txt
data_raven-1.0.0.dist-info/RECORD
