Metadata-Version: 2.1
Name: data-raven
Version: 1.0.0
Summary: A Python framework for building data quality tests
Home-page: https://github.com/tekkabroley/data-raven
Author: Alex Broley
Author-email: alex.broley@gmail.com
License: UNKNOWN
Platform: UNKNOWN
Classifier: Programming Language :: Python :: 3
Classifier: License :: OSI Approved :: MIT License
Classifier: Operating System :: OS Independent
Requires-Python: >=3.6
